{
    "openapi": "3.1.0",
    "info": {
        "title": "Marifatun API Documentation",
        "version": "1.0.0"
    },
    "servers": [
        {
            "url": "http://localhost/api"
        }
    ],
    "tags": [
        {
            "name": "Auth"
        },
        {
            "name": "ROLE ADMIN"
        },
        {
            "name": "ROLE MARIFATUN_USER"
        }
    ],
    "security": [
        {
            "http": []
        }
    ],
    "paths": {
        "/v1/auth/register": {
            "post": {
                "operationId": "auth.register",
                "summary": "POST /api/v1/auth/register",
                "tags": [
                    "Auth"
                ],
                "requestBody": {
                    "required": true,
                    "content": {
                        "application/json": {
                            "schema": {
                                "$ref": "#/components/schemas/RegisterRequest"
                            }
                        }
                    }
                },
                "responses": {
                    "200": {
                        "description": "",
                        "content": {
                            "application/json": {
                                "schema": {
                                    "type": "object"
                                }
                            }
                        }
                    },
                    "422": {
                        "$ref": "#/components/responses/ValidationException"
                    }
                },
                "security": []
            }
        },
        "/v1/auth/login": {
            "post": {
                "operationId": "auth.login",
                "summary": "POST /api/v1/auth/login",
                "tags": [
                    "Auth"
                ],
                "requestBody": {
                    "required": true,
                    "content": {
                        "application/json": {
                            "schema": {
                                "$ref": "#/components/schemas/LoginRequest"
                            }
                        }
                    }
                },
                "responses": {
                    "200": {
                        "description": "",
                        "content": {
                            "application/json": {
                                "schema": {
                                    "type": "object"
                                }
                            }
                        }
                    },
                    "422": {
                        "$ref": "#/components/responses/ValidationException"
                    }
                },
                "security": []
            }
        },
        "/v1/auth/forgot-password": {
            "post": {
                "operationId": "auth.forgotPassword",
                "summary": "POST /api/v1/auth/forgot-password",
                "tags": [
                    "Auth"
                ],
                "requestBody": {
                    "required": true,
                    "content": {
                        "application/json": {
                            "schema": {
                                "$ref": "#/components/schemas/ForgotPasswordRequest"
                            }
                        }
                    }
                },
                "responses": {
                    "200": {
                        "description": "",
                        "content": {
                            "application/json": {
                                "schema": {
                                    "type": "object"
                                }
                            }
                        }
                    },
                    "422": {
                        "$ref": "#/components/responses/ValidationException"
                    }
                },
                "security": []
            }
        },
        "/v1/auth/logout": {
            "post": {
                "operationId": "auth.logout",
                "summary": "POST /api/v1/auth/logout",
                "tags": [
                    "Auth"
                ],
                "responses": {
                    "200": {
                        "description": "",
                        "content": {
                            "application/json": {
                                "schema": {
                                    "type": "object"
                                }
                            }
                        }
                    },
                    "401": {
                        "$ref": "#/components/responses/AuthenticationException"
                    }
                }
            }
        },
        "/v1/users": {
            "get": {
                "operationId": "users.index",
                "summary": "GET /api/v1/users",
                "tags": [
                    "ROLE ADMIN"
                ],
                "parameters": [
                    {
                        "name": "per_page",
                        "in": "query",
                        "schema": {
                            "type": "integer",
                            "minimum": 1,
                            "maximum": 100
                        }
                    },
                    {
                        "name": "search",
                        "in": "query",
                        "schema": {
                            "type": [
                                "string",
                                "null"
                            ],
                            "maxLength": 255
                        }
                    },
                    {
                        "name": "active",
                        "in": "query",
                        "schema": {
                            "type": [
                                "string",
                                "null"
                            ],
                            "enum": [
                                "0",
                                "1",
                                "0",
                                "1",
                                "1",
                                "",
                                "true",
                                "false"
                            ]
                        }
                    },
                    {
                        "name": "date_from",
                        "in": "query",
                        "schema": {
                            "type": [
                                "string",
                                "null"
                            ],
                            "format": "date-time"
                        }
                    },
                    {
                        "name": "date_to",
                        "in": "query",
                        "schema": {
                            "type": [
                                "string",
                                "null"
                            ],
                            "format": "date-time"
                        }
                    },
                    {
                        "name": "sort_by",
                        "in": "query",
                        "schema": {
                            "type": [
                                "string",
                                "null"
                            ],
                            "enum": [
                                "createdDate",
                                "modifiedDate",
                                "name",
                                "email"
                            ]
                        }
                    },
                    {
                        "name": "sort_direction",
                        "in": "query",
                        "schema": {
                            "type": [
                                "string",
                                "null"
                            ],
                            "enum": [
                                "asc",
                                "desc"
                            ]
                        }
                    }
                ],
                "responses": {
                    "200": {
                        "description": "",
                        "content": {
                            "application/json": {
                                "schema": {
                                    "type": "object"
                                }
                            }
                        }
                    },
                    "401": {
                        "$ref": "#/components/responses/AuthenticationException"
                    },
                    "422": {
                        "$ref": "#/components/responses/ValidationException"
                    }
                }
            },
            "post": {
                "operationId": "users.store",
                "summary": "POST /api/v1/users",
                "tags": [
                    "ROLE ADMIN"
                ],
                "requestBody": {
                    "required": true,
                    "content": {
                        "application/json": {
                            "schema": {
                                "$ref": "#/components/schemas/CreateUserRequest"
                            }
                        }
                    }
                },
                "responses": {
                    "200": {
                        "description": "",
                        "content": {
                            "application/json": {
                                "schema": {
                                    "type": "object"
                                }
                            }
                        }
                    },
                    "401": {
                        "$ref": "#/components/responses/AuthenticationException"
                    },
                    "422": {
                        "$ref": "#/components/responses/ValidationException"
                    }
                }
            }
        },
        "/v1/users/{user}": {
            "get": {
                "operationId": "users.show",
                "summary": "GET /api/v1/users/{user}",
                "tags": [
                    "ROLE ADMIN"
                ],
                "parameters": [
                    {
                        "name": "user",
                        "in": "path",
                        "required": true,
                        "schema": {
                            "type": "string"
                        }
                    }
                ],
                "responses": {
                    "200": {
                        "description": "",
                        "content": {
                            "application/json": {
                                "schema": {
                                    "type": "object"
                                }
                            }
                        }
                    },
                    "401": {
                        "$ref": "#/components/responses/AuthenticationException"
                    }
                }
            },
            "put": {
                "operationId": "users.update",
                "summary": "PUT /api/v1/users/{user}",
                "tags": [
                    "ROLE ADMIN"
                ],
                "parameters": [
                    {
                        "name": "user",
                        "in": "path",
                        "required": true,
                        "schema": {
                            "type": "string"
                        }
                    }
                ],
                "requestBody": {
                    "content": {
                        "application/json": {
                            "schema": {
                                "$ref": "#/components/schemas/UpdateUserRequest"
                            }
                        }
                    }
                },
                "responses": {
                    "200": {
                        "description": "",
                        "content": {
                            "application/json": {
                                "schema": {
                                    "type": "object"
                                }
                            }
                        }
                    },
                    "401": {
                        "$ref": "#/components/responses/AuthenticationException"
                    },
                    "422": {
                        "$ref": "#/components/responses/ValidationException"
                    }
                }
            },
            "delete": {
                "operationId": "users.destroy",
                "summary": "DELETE /api/v1/users/{user}",
                "tags": [
                    "ROLE ADMIN"
                ],
                "parameters": [
                    {
                        "name": "user",
                        "in": "path",
                        "required": true,
                        "schema": {
                            "type": "string"
                        }
                    }
                ],
                "responses": {
                    "200": {
                        "description": "",
                        "content": {
                            "application/json": {
                                "schema": {
                                    "type": "object"
                                }
                            }
                        }
                    },
                    "401": {
                        "$ref": "#/components/responses/AuthenticationException"
                    }
                }
            }
        },
        "/v1/dashboard/admin": {
            "get": {
                "operationId": "dashboard.admin",
                "summary": "GET /api/v1/dashboard/admin",
                "tags": [
                    "ROLE ADMIN"
                ],
                "responses": {
                    "200": {
                        "description": "",
                        "content": {
                            "application/json": {
                                "schema": {
                                    "type": "object"
                                }
                            }
                        }
                    },
                    "401": {
                        "$ref": "#/components/responses/AuthenticationException"
                    }
                }
            }
        },
        "/v1/contents": {
            "get": {
                "operationId": "contents.index",
                "summary": "GET /api/v1/contents",
                "tags": [
                    "ROLE ADMIN"
                ],
                "responses": {
                    "200": {
                        "description": "",
                        "content": {
                            "application/json": {
                                "schema": {
                                    "type": "object"
                                }
                            }
                        }
                    },
                    "401": {
                        "$ref": "#/components/responses/AuthenticationException"
                    }
                }
            },
            "post": {
                "operationId": "contents.store",
                "summary": "POST /api/v1/contents",
                "tags": [
                    "ROLE ADMIN"
                ],
                "requestBody": {
                    "required": true,
                    "content": {
                        "application/json": {
                            "schema": {
                                "$ref": "#/components/schemas/CreateContentRequest"
                            }
                        }
                    }
                },
                "responses": {
                    "200": {
                        "description": "",
                        "content": {
                            "application/json": {
                                "schema": {
                                    "type": "object"
                                }
                            }
                        }
                    },
                    "401": {
                        "$ref": "#/components/responses/AuthenticationException"
                    },
                    "422": {
                        "$ref": "#/components/responses/ValidationException"
                    }
                }
            }
        },
        "/v1/contents/{content}": {
            "get": {
                "operationId": "contents.show",
                "summary": "GET /api/v1/contents/{content}",
                "tags": [
                    "ROLE ADMIN"
                ],
                "parameters": [
                    {
                        "name": "content",
                        "in": "path",
                        "required": true,
                        "schema": {
                            "type": "string"
                        }
                    }
                ],
                "responses": {
                    "200": {
                        "description": "",
                        "content": {
                            "application/json": {
                                "schema": {
                                    "type": "object"
                                }
                            }
                        }
                    },
                    "401": {
                        "$ref": "#/components/responses/AuthenticationException"
                    }
                }
            },
            "put": {
                "operationId": "contents.update",
                "summary": "PUT /api/v1/contents/{content}",
                "tags": [
                    "ROLE ADMIN"
                ],
                "parameters": [
                    {
                        "name": "content",
                        "in": "path",
                        "required": true,
                        "schema": {
                            "type": "string"
                        }
                    }
                ],
                "requestBody": {
                    "required": true,
                    "content": {
                        "application/json": {
                            "schema": {
                                "$ref": "#/components/schemas/UpdateContentRequest"
                            }
                        }
                    }
                },
                "responses": {
                    "200": {
                        "description": "",
                        "content": {
                            "application/json": {
                                "schema": {
                                    "type": "object"
                                }
                            }
                        }
                    },
                    "401": {
                        "$ref": "#/components/responses/AuthenticationException"
                    },
                    "422": {
                        "$ref": "#/components/responses/ValidationException"
                    }
                }
            },
            "delete": {
                "operationId": "contents.destroy",
                "summary": "DELETE /api/v1/contents/{content}",
                "tags": [
                    "ROLE ADMIN"
                ],
                "parameters": [
                    {
                        "name": "content",
                        "in": "path",
                        "required": true,
                        "schema": {
                            "type": "string"
                        }
                    }
                ],
                "responses": {
                    "200": {
                        "description": "",
                        "content": {
                            "application/json": {
                                "schema": {
                                    "type": "object"
                                }
                            }
                        }
                    },
                    "401": {
                        "$ref": "#/components/responses/AuthenticationException"
                    }
                }
            }
        },
        "/v1/dashboard/user": {
            "get": {
                "operationId": "dashboard.user",
                "summary": "GET /api/v1/dashboard/user",
                "tags": [
                    "ROLE MARIFATUN_USER"
                ],
                "responses": {
                    "200": {
                        "description": "",
                        "content": {
                            "application/json": {
                                "schema": {
                                    "type": "object"
                                }
                            }
                        }
                    },
                    "401": {
                        "$ref": "#/components/responses/AuthenticationException"
                    }
                }
            }
        },
        "/v1/user/contents/statistics": {
            "get": {
                "operationId": "user.contents.statistics",
                "summary": "GET /api/v1/user/contents/statistics",
                "tags": [
                    "ROLE MARIFATUN_USER"
                ],
                "responses": {
                    "200": {
                        "description": "",
                        "content": {
                            "application/json": {
                                "schema": {
                                    "type": "object"
                                }
                            }
                        }
                    },
                    "401": {
                        "$ref": "#/components/responses/AuthenticationException"
                    }
                }
            }
        },
        "/v1/user/contents": {
            "get": {
                "operationId": "user.contents.index",
                "summary": "GET /api/v1/user/contents",
                "tags": [
                    "ROLE MARIFATUN_USER"
                ],
                "responses": {
                    "200": {
                        "description": "",
                        "content": {
                            "application/json": {
                                "schema": {
                                    "type": "object"
                                }
                            }
                        }
                    },
                    "401": {
                        "$ref": "#/components/responses/AuthenticationException"
                    }
                }
            },
            "post": {
                "operationId": "user.contents.store",
                "summary": "POST /api/v1/user/contents",
                "tags": [
                    "ROLE MARIFATUN_USER"
                ],
                "requestBody": {
                    "required": true,
                    "content": {
                        "application/json": {
                            "schema": {
                                "$ref": "#/components/schemas/CreateContentRequest"
                            }
                        }
                    }
                },
                "responses": {
                    "200": {
                        "description": "",
                        "content": {
                            "application/json": {
                                "schema": {
                                    "type": "object"
                                }
                            }
                        }
                    },
                    "401": {
                        "$ref": "#/components/responses/AuthenticationException"
                    },
                    "422": {
                        "$ref": "#/components/responses/ValidationException"
                    }
                }
            }
        },
        "/v1/user/contents/{content}": {
            "get": {
                "operationId": "user.contents.show",
                "summary": "GET /api/v1/user/contents/{content}",
                "tags": [
                    "ROLE MARIFATUN_USER"
                ],
                "parameters": [
                    {
                        "name": "content",
                        "in": "path",
                        "required": true,
                        "schema": {
                            "type": "string"
                        }
                    }
                ],
                "responses": {
                    "200": {
                        "description": "",
                        "content": {
                            "application/json": {
                                "schema": {
                                    "type": "object"
                                }
                            }
                        }
                    },
                    "401": {
                        "$ref": "#/components/responses/AuthenticationException"
                    }
                }
            },
            "put": {
                "operationId": "user.contents.update",
                "summary": "PUT /api/v1/user/contents/{content}",
                "tags": [
                    "ROLE MARIFATUN_USER"
                ],
                "parameters": [
                    {
                        "name": "content",
                        "in": "path",
                        "required": true,
                        "schema": {
                            "type": "string"
                        }
                    }
                ],
                "requestBody": {
                    "required": true,
                    "content": {
                        "application/json": {
                            "schema": {
                                "$ref": "#/components/schemas/UpdateContentRequest"
                            }
                        }
                    }
                },
                "responses": {
                    "200": {
                        "description": "",
                        "content": {
                            "application/json": {
                                "schema": {
                                    "type": "object"
                                }
                            }
                        }
                    },
                    "401": {
                        "$ref": "#/components/responses/AuthenticationException"
                    },
                    "422": {
                        "$ref": "#/components/responses/ValidationException"
                    }
                }
            },
            "delete": {
                "operationId": "user.contents.destroy",
                "summary": "DELETE /api/v1/user/contents/{content}",
                "tags": [
                    "ROLE MARIFATUN_USER"
                ],
                "parameters": [
                    {
                        "name": "content",
                        "in": "path",
                        "required": true,
                        "schema": {
                            "type": "string"
                        }
                    }
                ],
                "responses": {
                    "200": {
                        "description": "",
                        "content": {
                            "application/json": {
                                "schema": {
                                    "type": "object"
                                }
                            }
                        }
                    },
                    "401": {
                        "$ref": "#/components/responses/AuthenticationException"
                    }
                }
            }
        }
    },
    "components": {
        "securitySchemes": {
            "http": {
                "type": "http",
                "description": "Bearer dari `POST /api/v1/auth/login`. Header: `Authorization: Bearer {token}`",
                "scheme": "bearer"
            }
        },
        "schemas": {
            "CreateContentRequest": {
                "type": "object",
                "properties": {
                    "content_type": {
                        "type": "string",
                        "enum": [
                            "linkedin",
                            "x",
                            "thread",
                            "facebook",
                            "email_marketing",
                            "video_script"
                        ]
                    },
                    "topic": {
                        "type": "string"
                    },
                    "keywords": {
                        "type": [
                            "string",
                            "null"
                        ],
                        "maxLength": 1000
                    },
                    "target_audience": {
                        "type": [
                            "string",
                            "null"
                        ],
                        "maxLength": 255
                    },
                    "tone": {
                        "type": "string",
                        "enum": [
                            "formal",
                            "casual",
                            "persuasive",
                            "friendly",
                            "professional",
                            "inspirational",
                            "humorous"
                        ]
                    },
                    "video_platform": {
                        "type": [
                            "string",
                            "null"
                        ],
                        "maxLength": 64
                    },
                    "video_key_message": {
                        "type": [
                            "string",
                            "null"
                        ],
                        "maxLength": 2000
                    },
                    "video_cta": {
                        "type": [
                            "string",
                            "null"
                        ],
                        "maxLength": 500
                    }
                },
                "required": [
                    "content_type",
                    "topic",
                    "tone"
                ],
                "title": "CreateContentRequest"
            },
            "CreateUserRequest": {
                "type": "object",
                "properties": {
                    "name": {
                        "type": "string",
                        "maxLength": 100
                    },
                    "email": {
                        "type": "string",
                        "format": "email"
                    },
                    "password": {
                        "type": "string",
                        "minLength": 6
                    },
                    "role": {
                        "type": [
                            "string",
                            "null"
                        ],
                        "enum": [
                            "ADMIN",
                            "MARIFATUN_USER"
                        ]
                    },
                    "active": {
                        "type": "boolean"
                    }
                },
                "required": [
                    "name",
                    "email",
                    "password"
                ],
                "title": "CreateUserRequest"
            },
            "ForgotPasswordRequest": {
                "type": "object",
                "properties": {
                    "email": {
                        "type": "string",
                        "format": "email"
                    },
                    "new_password": {
                        "type": "string",
                        "minLength": 6
                    }
                },
                "required": [
                    "email",
                    "new_password"
                ],
                "title": "ForgotPasswordRequest"
            },
            "LoginRequest": {
                "type": "object",
                "properties": {
                    "email": {
                        "type": "string",
                        "format": "email"
                    },
                    "password": {
                        "type": "string",
                        "minLength": 6
                    }
                },
                "required": [
                    "email",
                    "password"
                ],
                "title": "LoginRequest"
            },
            "RegisterRequest": {
                "type": "object",
                "properties": {
                    "name": {
                        "type": "string",
                        "maxLength": 100
                    },
                    "email": {
                        "type": "string",
                        "format": "email"
                    },
                    "password": {
                        "type": "string",
                        "minLength": 6
                    },
                    "password_confirmation": {
                        "type": "string",
                        "minLength": 6
                    }
                },
                "required": [
                    "name",
                    "email",
                    "password",
                    "password_confirmation"
                ],
                "title": "RegisterRequest"
            },
            "UpdateContentRequest": {
                "type": "object",
                "properties": {
                    "content_type": {
                        "type": "string",
                        "enum": [
                            "linkedin",
                            "x",
                            "thread",
                            "facebook",
                            "email_marketing",
                            "video_script"
                        ]
                    },
                    "topic": {
                        "type": "string"
                    },
                    "keywords": {
                        "type": [
                            "string",
                            "null"
                        ],
                        "maxLength": 1000
                    },
                    "target_audience": {
                        "type": [
                            "string",
                            "null"
                        ],
                        "maxLength": 255
                    },
                    "tone": {
                        "type": "string",
                        "enum": [
                            "formal",
                            "casual",
                            "persuasive",
                            "friendly",
                            "professional",
                            "inspirational",
                            "humorous"
                        ]
                    },
                    "video_platform": {
                        "type": [
                            "string",
                            "null"
                        ],
                        "maxLength": 64
                    },
                    "video_key_message": {
                        "type": [
                            "string",
                            "null"
                        ],
                        "maxLength": 2000
                    },
                    "video_cta": {
                        "type": [
                            "string",
                            "null"
                        ],
                        "maxLength": 500
                    }
                },
                "required": [
                    "content_type",
                    "topic",
                    "tone"
                ],
                "title": "UpdateContentRequest"
            },
            "UpdateUserRequest": {
                "type": "object",
                "properties": {
                    "name": {
                        "type": "string",
                        "maxLength": 100
                    },
                    "email": {
                        "type": "string",
                        "format": "email"
                    },
                    "password": {
                        "type": [
                            "string",
                            "null"
                        ],
                        "minLength": 6
                    },
                    "role": {
                        "type": [
                            "string",
                            "null"
                        ],
                        "enum": [
                            "ADMIN",
                            "MARIFATUN_USER"
                        ]
                    },
                    "active": {
                        "type": "boolean"
                    }
                },
                "title": "UpdateUserRequest"
            }
        },
        "responses": {
            "ValidationException": {
                "description": "Validation error",
                "content": {
                    "application/json": {
                        "schema": {
                            "type": "object",
                            "properties": {
                                "message": {
                                    "type": "string",
                                    "description": "Errors overview."
                                },
                                "errors": {
                                    "type": "object",
                                    "description": "A detailed description of each field that failed validation.",
                                    "additionalProperties": {
                                        "type": "array",
                                        "items": {
                                            "type": "string"
                                        }
                                    }
                                }
                            },
                            "required": [
                                "message",
                                "errors"
                            ]
                        }
                    }
                }
            },
            "AuthenticationException": {
                "description": "Unauthenticated",
                "content": {
                    "application/json": {
                        "schema": {
                            "type": "object",
                            "properties": {
                                "message": {
                                    "type": "string",
                                    "description": "Error overview."
                                }
                            },
                            "required": [
                                "message"
                            ]
                        }
                    }
                }
            }
        }
    }
}